bas/__init__.py
bas/cli/__init__.py
bas/cli/cli.py
bas/cli/g2p.py
bas/cli/maus.py
bas/cli/subtitle.py
bas/services/__init__.py
bas/services/g2p.py
bas/services/maus.py
bas/services/pipeline.py
bas/services/subtitle.py
bas/services/utils.py
bas-0.0.2.dist-info/METADATA
bas-0.0.2.dist-info/RECORD
bas-0.0.2.dist-info/WHEEL
bas-0.0.2.dist-info/entry_points.txt
bas-0.0.2.dist-info/top_level.txt
