Metadata-Version: 2.1
Name: bas
Version: 0.0.2
Summary: bas client and cli
Home-page: https://github.com/youkaclub/bas
Author-email: youka.club@gmail.com
License: UNKNOWN
Platform: UNKNOWN
Requires-Dist: click (==7.0)
Requires-Dist: requests (==2.21.0)
